.gitignore
.travis.yml
README.rst
ploghandler.py
setup.py
test.py
tox.ini
ploghandler.egg-info/PKG-INFO
ploghandler.egg-info/SOURCES.txt
ploghandler.egg-info/dependency_links.txt
ploghandler.egg-info/top_level.txt