Metadata-Version: 1.1
Name: ploghandler
Version: 0.5.0
Summary: Provides concurrent rotating file handler for posix-compatible OSes.
Home-page: https://github.com/NightBlues/ploghandler
Author: Vadim Radovel
Author-email: vadim@radovel.ru
License: GPLv3
Platform: posix
Classifier: Development Status :: 4 - Beta
Classifier: Intended Audience :: Developers
Classifier: Operating System :: MacOS :: MacOS X
Classifier: Operating System :: POSIX
Classifier: Operating System :: Unix
Classifier: Programming Language :: Python :: 2
Classifier: Topic :: Software Development :: Libraries :: Python Modules
Classifier: Topic :: System :: Logging
